pcapprox/__init__.py
pcapprox/interface.py
pcapprox/learning.py
pcapprox/networks.py
pcapprox/networks.py.bak
pcapprox/utils.py
pcapprox-0.3.0.dist-info/LICENSE
pcapprox-0.3.0.dist-info/WHEEL
pcapprox-0.3.0.dist-info/METADATA
pcapprox-0.3.0.dist-info/RECORD
