Metadata-Version: 2.1
Name: pcapprox
Version: 0.3.0
Summary: A Python package for parameterized convex approximators
License: MIT
Author: JinraeKim
Author-email: kjl950403@gmail.com
Requires-Python: >=3.8,<3.9
Classifier: License :: OSI Approved :: MIT License
Classifier: Programming Language :: Python :: 3
Classifier: Programming Language :: Python :: 3.8
Requires-Dist: cvxpy (>=1.2.1,<2.0.0)
Requires-Dist: cvxpylayers (>=0.1.5,<0.2.0)
Requires-Dist: numpy (>=1.23.4,<2.0.0)
Requires-Dist: pathlib (>=1.0.1,<2.0.0)
Requires-Dist: torch (>=1.12.0,<2.0.0)
Requires-Dist: tqdm (>=4.64.1,<5.0.0)
